mcv_api/models/Course.py
mcv_api/session/session.py
mcv_api/utils/utils.py
mcv_api_python_unofficial-0.1.0.dist-info/METADATA
mcv_api_python_unofficial-0.1.0.dist-info/WHEEL
mcv_api_python_unofficial-0.1.0.dist-info/RECORD
